firebase_populator/__init__.py
firebase_populator/firebase_populator.py
firebase_populator-0.1.0.dist-info/METADATA
firebase_populator-0.1.0.dist-info/WHEEL
firebase_populator-0.1.0.dist-info/top_level.txt
firebase_populator-0.1.0.dist-info/RECORD
