Metadata-Version: 2.1
Name: firebase-populator
Version: 0.1.0
Summary: A package to populate Firebase Firestore.
Author: Your Name
Author-email: your.email@example.com
Requires-Dist: firebase-admin
